behavioralsignals/__init__.py
behavioralsignals/base.py
behavioralsignals/behavioral.py
behavioralsignals/client.py
behavioralsignals/configuration.py
behavioralsignals/deepfakes.py
behavioralsignals/models.py
behavioralsignals/utils.py
behavioralsignals/generated/__init__.py
behavioralsignals/generated/api_pb2.py
behavioralsignals/generated/api_pb2.pyi
behavioralsignals/generated/api_pb2_grpc.py
behavioralsignals-0.3.0.dist-info/licenses/LICENSE
behavioralsignals-0.3.0.dist-info/METADATA
behavioralsignals-0.3.0.dist-info/WHEEL
behavioralsignals-0.3.0.dist-info/top_level.txt
behavioralsignals-0.3.0.dist-info/RECORD
