Metadata-Version: 2.4
Name: behavioralsignals
Version: 0.3.0
Summary: Python SDK for Behavioral Signals API
License:                                  Apache License
Project-URL: Repository, https://github.com/BehavioralSignalTechnologies/behavioralsignals-python
Classifier: Intended Audience :: Developers
Classifier: Programming Language :: Python :: 3
Classifier: Programming Language :: Python :: 3.10
Classifier: Programming Language :: Python :: 3.11
Classifier: Programming Language :: Python :: 3.12
Classifier: Programming Language :: Python :: 3.13
Classifier: Operating System :: OS Independent
Classifier: License :: OSI Approved :: Apache Software License
Requires-Python: >=3.10
License-File: LICENSE
Requires-Dist: grpcio>=1.64.0
Requires-Dist: protobuf>=6.31.1
Requires-Dist: pydantic>=2.11.7
Requires-Dist: pydub>=0.25.1
Requires-Dist: requests>=2.32.4
Requires-Dist: audioop-lts; python_version >= "3.13"
Provides-Extra: dev
Requires-Dist: grpcio-tools>=1.64.0; extra == "dev"
Requires-Dist: ruff; extra == "dev"
Dynamic: license-file
